vnnum2word/__init__.py
vnnum2word/main.py
vnnum2word-0.3.0.dist-info/METADATA
vnnum2word-0.3.0.dist-info/WHEEL
vnnum2word-0.3.0.dist-info/licenses/LICENSE
vnnum2word-0.3.0.dist-info/RECORD
