Metadata-Version: 2.4
Name: vnnum2word
Version: 0.3.0
Summary: Convert Vietnamese numbers to words
Project-URL: Homepage, https://github.com/jayll-packages/vnnum2word
Author-email: JayLL <jayll13.work@gmail.com>
License: MIT License
License-File: LICENSE
Keywords: nlp,number,vietnamese,words
Requires-Python: >=3.6
